setup.py
facade/__init__.py
facade/facade_device.py
facade/facade_device_type.py
facade/facade_error_code.py
facade/libfacade.py
facade/libfacade_h.py
facade/video_facade_device.py
pyfacade.egg-info/PKG-INFO
pyfacade.egg-info/SOURCES.txt
pyfacade.egg-info/dependency_links.txt
pyfacade.egg-info/requires.txt
pyfacade.egg-info/top_level.txt